{
  "dependencies": [
    {
      "name": "adaptmesh",
      "type": "runtime"
    },
    {
      "name": "gmsh",
      "type": "runtime"
    },
    {
      "name": "numpy",
      "type": "runtime"
    },
    {
      "name": "pygmsh",
      "type": "runtime"
    },
    {
      "name": "python",
      "version": "^3.12.0",
      "type": "runtime"
    },
    {
      "name": "shapely",
      "version": "^2.0.0",
      "type": "runtime"
    },
    {
      "name": "pytest",
      "version": "7.4.3",
      "type": "test"
    }
  ],
  "//": "~~ Generated by projen. To modify, edit .projenrc.js and run \"npx projen\"."
}
